<?xml version="1.0" encoding="UTF-8"?>
<window>
	<defaultcontrol always="true">29</defaultcontrol>
	<include>OpenCloseAnimation</include>
	<controls>
		<control type="group">
			<left>9</left>
			<top>210</top>
			<control type="image">
				<description>background image</description>
				<left>16</left>
				<top>16</top>
				<width>1870</width>
				<height>628</height>
				<texture border="18">dialogs/dialog-bg2.png</texture>
			</control>
			<control type="image">
				<left>32</left>
				<top>88</top>
				<width>495</width>
				<height>540</height>
				<texture colordiffuse="dialogInner">dialogs/black.png</texture>
			</control>
			<control type="image">
				<left>542</left>
				<top>88</top>
				<width>495</width>
				<height>540</height>
				<texture colordiffuse="dialogInner">dialogs/black.png</texture>
			</control>
			<control type="image">
				<left>1052</left>
				<top>88</top>
				<width>495</width>
				<height>540</height>
				<texture colordiffuse="dialogInner">dialogs/black.png</texture>
			</control>
			<control type="group">
				<control type="group">
					<description>Group list</description>
					<control type="label">
						<description>name label</description>
						<left>32</left>
						<top>32</top>
						<width>495</width>
						<height>40</height>
						<font>font15</font>
						<align>center</align>
						<textcolor>dialogheader</textcolor>
						<textoffsetx>15</textoffsetx>
						<label>31506</label>
					</control>
					<control type="list" id="13">
						<left>32</left>
						<top>88</top>
						<width>495</width>
						<height>540</height>
						<onup>13</onup>
						<ondown>13</ondown>
						<onleft>29</onleft>
						<onright>73</onright>
						<pagecontrol>73</pagecontrol>
						<scrolltime tween="quadratic" easing="out">200</scrolltime>
						<orientation>vertical</orientation>
						<itemlayout height="60">
							<control type="image">
								<width>495</width>
								<height>60</height>
								<texture border="4">dialogs/separator2.png</texture>
							</control>
							<control type="label">
								<width>495</width>
								<height>60</height>
								<font>font14</font>
								<textoffsetx>15</textoffsetx>
								<textcolor>grey</textcolor>
								<info>ListItem.Label</info>
							</control>
						</itemlayout>
						<focusedlayout height="60">
							<control type="image">
								<width>495</width>
								<height>60</height>
								<texture border="4">dialogs/separator2.png</texture>
							</control>
							<control type="image">
								<width>495</width>
								<height>60</height>
								<texture border="4" colordiffuse="themecolor">dialogs/listselect_fo.png</texture>
								<visible>Control.HasFocus(13)</visible>
							</control>
							<control type="label">
								<width>495</width>
								<height>60</height>
								<font>font14</font>
								<textoffsetx>15</textoffsetx>
								<info>ListItem.Label</info>
							</control>
						</focusedlayout>
					</control>
					<control type="scrollbar" id="73">
						<left>528</left>
						<top>88</top>
						<width>12</width>
						<height>540</height>
						<texturesliderbar border="2">scrollbar/texturesliderbar_ver.png</texturesliderbar>
						<texturesliderbarfocus border="2" colordiffuse="themecolor">scrollbar/texturesliderbarfocus_ver.png</texturesliderbarfocus>
						<onleft>13</onleft>
						<onright>11</onright>
						<showonepage>false</showonepage>
						<orientation>vertical</orientation>
					</control>
				</control>
				<control type="group">
					<description>Channels list</description>
					<control type="label" id="21">
						<description>name label</description>
						<left>542</left>
						<top>32</top>
						<width>495</width>
						<height>40</height>
						<font>font15</font>
						<align>center</align>
						<textcolor>dialogheader</textcolor>
						<textoffsetx>15</textoffsetx>
						<label>31506</label>
					</control>
					<control type="list" id="11">
						<left>542</left>
						<top>88</top>
						<width>495</width>
						<height>540</height>
						<onup>11</onup>
						<ondown>11</ondown>
						<onleft>73</onleft>
						<onright>71</onright>
						<pagecontrol>71</pagecontrol>
						<scrolltime>200</scrolltime>
						<itemlayout height="60">
							<control type="image">
								<width>495</width>
								<height>60</height>
								<texture border="4">dialogs/separator2.png</texture>
							</control>
							<control type="label">
								<width>495</width>
								<height>60</height>
								<font>font14</font>
								<textoffsetx>15</textoffsetx>
								<textcolor>grey</textcolor>
								<info>ListItem.Label</info>
							</control>
						</itemlayout>
						<focusedlayout height="60">
							<control type="image">
								<width>495</width>
								<height>60</height>
								<texture border="4">dialogs/separator2.png</texture>
							</control>
							<control type="image">
								<width>495</width>
								<height>60</height>
								<texture border="4" colordiffuse="themecolor">dialogs/listselect_fo.png</texture>
								<visible>Control.HasFocus(11)</visible>
							</control>
							<control type="label">
								<width>495</width>
								<height>60</height>
								<font>font14</font>
								<textoffsetx>15</textoffsetx>
								<info>ListItem.Label</info>
							</control>
						</focusedlayout>
					</control>
					<control type="scrollbar" id="71">
						<left>1039</left>
						<top>88</top>
						<width>12</width>
						<height>540</height>
						<texturesliderbar border="2">scrollbar/texturesliderbar_ver.png</texturesliderbar>
						<texturesliderbarfocus border="2" colordiffuse="themecolor">scrollbar/texturesliderbarfocus_ver.png</texturesliderbarfocus>
						<onleft>11</onleft>
						<onright>12</onright>
						<showonepage>false</showonepage>
						<orientation>vertical</orientation>
					</control>
				</control>
				<control type="group">
					<description>Grouped Channels list</description>
					<control type="label" id="22">
						<description>name label</description>
						<left>1052</left>
						<top>32</top>
						<width>495</width>
						<height>40</height>
						<font>font15</font>
						<textcolor>dialogheader</textcolor>
						<align>center</align>
						<textoffsetx>15</textoffsetx>
						<label>31506</label>
					</control>
					<control type="list" id="12">
						<left>1052</left>
						<top>88</top>
						<width>495</width>
						<height>540</height>
						<onup>12</onup>
						<ondown>12</ondown>
						<onleft>71</onleft>
						<onright>72</onright>
						<pagecontrol>72</pagecontrol>
						<scrolltime>200</scrolltime>
						<itemlayout height="60">
							<control type="image">
								<width>495</width>
								<height>60</height>
								<texture border="4">dialogs/separator2.png</texture>
							</control>
							<control type="label">
								<width>495</width>
								<height>60</height>
								<font>font14</font>
								<textoffsetx>15</textoffsetx>
								<textcolor>grey</textcolor>
								<info>ListItem.Label</info>
							</control>
						</itemlayout>
						<focusedlayout height="60">
							<control type="image">
								<width>495</width>
								<height>60</height>
								<texture border="4">dialogs/separator2.png</texture>
							</control>
							<control type="image">
								<width>495</width>
								<height>60</height>
								<texture border="4" colordiffuse="themecolor">dialogs/listselect_fo.png</texture>
								<visible>Control.HasFocus(12)</visible>
							</control>
							<control type="label">
								<width>495</width>
								<height>60</height>
								<font>font14</font>
								<textoffsetx>15</textoffsetx>
								<info>ListItem.Label</info>
							</control>
						</focusedlayout>
					</control>
					<control type="scrollbar" id="72">
						<left>1547</left>
						<top>88</top>
						<width>12</width>
						<height>540</height>
						<texturesliderbar border="2">scrollbar/texturesliderbar_ver.png</texturesliderbar>
						<texturesliderbarfocus border="2" colordiffuse="themecolor">scrollbar/texturesliderbarfocus_ver.png</texturesliderbarfocus>
						<onleft>12</onleft>
						<onright>26</onright>
						<showonepage>false</showonepage>
						<orientation>vertical</orientation>
					</control>
				</control>
			</control>
			<!-- right group -->
			<control type="group">
				<left>1560</left>
				<top>88</top>
				<control type="image">
					<width>310</width>
					<height>540</height>
					<texture colordiffuse="dialogInner">dialogs/black.png</texture>
				</control>
				<control type="grouplist" id="9000">
					<onleft>72</onleft>
					<onright>13</onright>
					<onup>9000</onup>
					<ondown>9000</ondown>
					<control type="button" id="29">
						<description>OK</description>
						<width>310</width>
						<label>186</label>
					</control>
					<control type="button" id="26">
						<description>Add Group</description>
						<width>310</width>
						<label>31503</label>
					</control>
					<control type="button" id="27">
						<description>Rename Group</description>
						<width>310</width>
						<label>31504</label>
					</control>
					<control type="radiobutton" id="25">
						<description>Hide Group</description>
						<width>310</width>
						<label>19289</label>
					</control>
					<control type="button" id="28">
						<description>Delete Group</description>
						<width>310</width>
						<label>31505</label>
					</control>
				</control>
			</control>
		</control>
	</controls>
</window>